asgihandler/License.py
asgihandler/__init__.py
asgihandler/__version__.py
asgihandler/core.py
asgihandler/handler.py
asgihandler/userCheck.py
asgihandler-0.5.9.dist-info/LICENSE
asgihandler-0.5.9.dist-info/METADATA
asgihandler-0.5.9.dist-info/WHEEL
asgihandler-0.5.9.dist-info/top_level.txt
asgihandler-0.5.9.dist-info/RECORD
