Metadata-Version: 2.1
Name: asgihandler
Version: 0.5.9
Summary: ASGIHandler
Home-page: https://github.com/GreaterWMS/GreaterWMS
Author: Singosgu
Author-email: singosgu@gmail.com
License: MIT
Classifier: License :: OSI Approved :: MIT License
Classifier: Programming Language :: Python
Classifier: Programming Language :: Python :: 3
Classifier: Programming Language :: Python :: 3.9
Classifier: Programming Language :: Python :: Implementation :: CPython
Classifier: Programming Language :: Python :: Implementation :: PyPy
Requires-Python: >=3.6.0
License-File: LICENSE
Requires-Dist: requests
